README.md
setup.cfg
setup.py
bin/caspredict
bin/repeatTrain
bin/repeatType
caspredict/__init__.py
caspredict/castyping.py
caspredict/controller.py
caspredict/crisprcas.py
caspredict/hmmer.py
caspredict/minced.py
caspredict/plot.py
caspredict/prodigal.py
caspredict/repeat.py
caspredict/xgb.py
caspredict/xgbtrain.py
caspredict.egg-info/PKG-INFO
caspredict.egg-info/SOURCES.txt
caspredict.egg-info/dependency_links.txt
caspredict.egg-info/requires.txt
caspredict.egg-info/top_level.txt