Metadata-Version: 2.1
Name: caspredict
Version: 0.5.4
Summary: Automatic detection and subtyping of CRISPR-Cas operons
Home-page: https://github.com/russel88/caspredict
Author: Jakob Russel
Author-email: russel2620@gmail.com
License: UNKNOWN
Download-URL: https://github.com/Russel88/CasPredict/archive/v0.5.4.tar.gz
Platform: UNKNOWN
Classifier: Programming Language :: Python :: 3
Classifier: License :: OSI Approved :: MIT License
Classifier: Operating System :: OS Independent
Classifier: Topic :: Scientific/Engineering :: Bio-Informatics
Classifier: Topic :: Software Development :: Libraries :: Python Modules
Classifier: Development Status :: 4 - Beta
Requires-Python: >=3.8
